Workbook

Sheet Executive Summary
B2: Bed, Bath & Beyond | I2: Class info | L2: Group info
B3: Executive Summary | I3: Professor | J3: Dr. Bharadwaj Kannan | L3: Student name | M3: Zachary Nickolas | N3: Thor Skogum
I4: Semester | J4: Spring 2026 | M4: Dionysis Petratos | N4: Ryan Tarapchak | XEV4: Helper tables | XEW4: 38164 | XEX4: 37797 | XEY4: 37431
I5: Class | J5: FIN 871 | M5: Shubh Savani
C8: Financial analysis summary | XEV8: ='Historical Analysis'!C15 -> Operating margins | XEW8: {='Historical Analysis'!E15:G15} -> 0.14277484 | XEX8: 0.13097831 | XEY8: 0.11820509
XEV9: ='Historical Analysis'!C19 -> Return on Equity | XEW9: {='Historical Analysis'!E19:G19} -> 0.20065601 | XEX9: 0.23735023 | XEY9: 0.22978202
XEV11: Tax shield | XEW11: ='Scenario Analysis'!F44 -> 244986.28 | XEX11: ='Scenario Analysis'!G44 -> 489972.56
XEV12: Distress costs | XEW12: ='Scenario Analysis'!F47 -> 39470.914 | XEX12: ='Scenario Analysis'!G47 -> 980139.99
XEV13: Value added | XEW13: =XEW11-XEW12 -> 205515.37 | XEX13: =XEX11-XEX12 -> -490167.43
C29: Despite strong growth and margin expansion (+250bps), shareholder returns have decoupled from performance. ROE dropped to 20.1% as the Current Ratio ballooned to 2.56x, signaling urgent need to return 'lazy capital' to shareholders.
C34: Capital Structure recommendation summary
C36: Metric | E36: Status Quo (2004) | F36: Scenario A (Recommended) | G36: Scenario B (Risky)
C38: ='Scenario Analysis'!B53 -> Implied share price ($) | E38: ='Scenario Analysis'!E53 -> 37 | F38: ='Scenario Analysis'!F53 -> 37.742788 | G38: ='Scenario Analysis'!G53 -> 35.110985
C39: =Inputs!K11 -> Average Credit Rating | E39: =Inputs!M11 -> AAA | F39: =Inputs!N11 -> A | G39: =Inputs!O11 -> B
C40: ='Scenario Analysis'!B39 -> Adjusted EPS-diluted ($) | E40: ='Scenario Analysis'!E39 -> 1.3110708 | F40: ='Scenario Analysis'!F39 -> 1.3539062 | G40: ='Scenario Analysis'!G39 -> 1.2681663
C41: =Inputs!K13 -> Distress Probability | E41: =Inputs!M13 -> 0 | F41: =Inputs!N13 -> 0.01815 | G41: =Inputs!O13 -> 0.4507
C43: ='Scenario Analysis'!B49 -> Levered value | E43: ='Scenario Analysis'!E49 -> 10873530 | F43: ='Scenario Analysis'!F49 -> 11079045 | G43: ='Scenario Analysis'!G49 -> 10383363
C44: ='Scenario Analysis'!B50 -> Return on Equity | E44: ='Scenario Analysis'!E50 -> 0.2006561 | F44: ='Scenario Analysis'!F50 -> 0.39246039 | G44: ='Scenario Analysis'!G50 -> 1.0342707
C46: Recommendation: Adopt 40% Debt Recapitalization We recommend distributing $400M in excess cash and issuing $636M in debt (40% Debt-to-Capital) to repurchase shares. - Unlocks Shareholder Value: Increases the implied share price from $37.00 to $37.74 by capturing the Interest Tax Shield. - Optimizes Efficiency: Improves ROE from 20.1% to 39.2% without compromising operational flexibility. - Maintains Financial Safety: Preserves an Investment Grade "A" Credit Rating (1.82% default probability), balancing growth with stability. - Rejects 80% Option: While the 80% scenario maximizes EPS, it destroys firm value (Price drops to $35.11) due to the excessive distress costs of a "Junk" (B) credit rating.

Sheet Inputs
B2: Bed, Bath & Beyond
B3: Select Financial Information
B6: Fiscal Year Ended | E6: 37987 | F6: =EOMONTH(E6,-11) -> 37680 | G6: =EOMONTH(F6,-11) -> 37346 | H6: =EOMONTH(G6,-11) -> 37011 | K6: Scenario | M6: Actual | N6: A | O6: B | P6: Notes | R6: Exhibit 7A & 9 | T6: AAA | U6: AA | V6: A | W6: BBB | X6: BB | Y6: B | Z6: CCC
B8: Select Income Statement Data | K8: Scenario Drivers | R8: Scenario Drivers
B10: Net sales ($) | E10: 4477981 | F10: 3665164 | G10: 2927962 | H10: 2396655 | J10: =1 -> 1 | K10: Target debt % | M10: 0 | N10: 0.4 | O10: 0.8 | P10: Given case scenarios | R10: Total debt/capital (%) | T10: 5 | U10: 35.9 | V10: 42.6 | W10: 47 | X10: 57.7 | Y10: 75.1 | Z10: 91.7
B11: Cost of sales | E11: 2601317 | F11: 2146617 | G11: 1720396 | H11: 0 | J11: 2 | K11: Average Credit Rating | M11: =T6 -> AAA | N11: =V6 -> A | O11: =Y6 -> B | P11: Exhibit 7A: Based on total D/V assumed in (1) | R11: Average default rates, past 15 years | T11: 0.0052 | U11: 0.0131 | V11: 0.0232 | W11: 0.0664 | X11: 0.1952 | Y11: 0.3576 | Z11: 0.5438
J12: 3 | K12: Interest Rate | M12: 0 | N12: =AVERAGE(U13:V13) -> 0.05615 | O12: =AVERAGE(Y13:Z13) -> 0.08625 | P12: Exhibit 9: Average rate based on credit rating in (2)
B13: Gross profit | E13: =E10-E11 -> 1876664 | F13: =F10-F11 -> 1518547 | G13: =G10-G11 -> 1207566 | H13: 986459 | J13: 4 | K13: Distress Probability | M13: 0 | N13: =AVERAGE(U11:V11) -> 0.01815 | O13: =AVERAGE(Y11:Z11) -> 0.4507 | P13: Exhibit 7A: Average default rates based on credit rating in (2) | R13: Corporate bond rates | T13: 0.0533 | U13: 0.0548 | V13: 0.0575 | W13: 0.061 | X13: 0.066 | Y13: 0.0775 | Z13: 0.095
B14: Operating profit | E14: 639343 | F14: 480057 | G14: 346100 | H14: 272838
K15: Model Assumptions
B16: Interest income | E16: 10202 | F16: 11291 | G16: 10972 | H16: 0
B17: EBIT | E17: =E14+E16 -> 649545 | F17: =F14+F16 -> 491348 | G17: =G14+G16 -> 357072 | H17: =H14+H16 -> 272838 | K17: Share price ($) | M17: 37 | P17: Given in case study
K18: Excess Cash | M18: 400000 | P18: Given in case study
B19: Interest expense | E19: 0 | F19: 0 | G19: 0 | H19: 0 | K19: Tax rate | M19: 0.385 | P19: Exhibit 8: Assumed tax rate given
K20: Distress costs (% of firm value) | M20: 0.2 | P20: Gemini AI : Average direct + indirect costs for distressed retail company
B21: Net earnings | E21: 399470 | F21: 302179 | G21: 219599 | H21: 171922
K22: Risk free rate (10-yr T.Bond) | M22: 0.0383 | P22: Exhibit 9: Ten year Treasury bond
B23: Basic EPS ($) | E23: 1.35 | F23: 1.03 | G23: 0.76 | H23: - | K23: Implied rate earned on cash | M23: =E16/E41 -> 0.011772512 | P23: Exhibit 8: Calculated based on interest income & cash data
B24: Diluted EPS ($) | E24: 1.31 | F24: 1 | G24: 0.74 | H24: 0.59
B26: Average shares outstanding-basic | E26: 296854 | F26: 292927 | G26: 289877 | H26: 0
B27: Average shares outstanding-diluted | E27: 304690 | F27: 301147 | G27: 298667 | H27: 0
B30: Select Operating Data
B32: Stores open - end of period | E32: 575 | F32: 490 | G32: 396 | H32: 311
B33: Total square footage - end of period | E33: 19353000 | F33: 17255000 | G33: 14724000 | H33: 12204000
B34: % increase in comparable same-store sales | E34: 0.063 | F34: 0.079 | G34: 0.071 | H34: 0.05
B36: Select Balance Sheet Data
B38: Cash and cash equivalents | E38: 825015 | F38: 515670 | G38: 429496 | H38: 0
B39: Short term investment securities | E39: 41580 | F39: 100927 | G39: 0 | H39: 0
B41: Total cash | E41: =E38+E39 -> 866595 | F41: =F38+F39 -> 616597 | G41: =G38+G39 -> 429496 | H41: 0
B43: Merchandise inventory | E43: 1012334 | F43: 915671 | G43: 752972 | H43: 0
B45: Total current assets | E45: 1969286 | F45: 1594391 | G45: 1226717 | H45: 0
B46: Total assets | E46: 2865023 | F46: 2188842 | G46: 1647517 | H46: 1195725
B48: Working capital ($) | E48: 1199752 | F48: 914220 | G48: 715439 | H48: 1195725
B50: Total current liabilities | E50: 769534 | F50: 680171 | G50: 511278 | H50: 0
B51: Total liabilities | E51: 874203 | F51: 736921 | G51: 553167 | H51: 0
B53: Long term debt | E53: 0 | F53: 0 | G53: 0 | H53: 0
B55: Shareholders' equity | E55: 1990820 | F55: 1451921 | G55: 1094350 | H55: 817018

Sheet Historical Analysis
B2: Bed, Bath & Beyond
B3: Historical Analysis (up to 2004)
B6: Fiscal Year Ended | E6: 37987 | F6: =EOMONTH(E6,-11) -> 37680 | G6: =EOMONTH(F6,-11) -> 37346 | J6: Trend | L6: Notes
B8: Growth Ratios
C9: Sales | E9: =(Inputs!E10/Inputs!F10)-1 -> 0.22176825 | F9: =(Inputs!F10/Inputs!G10)-1 -> 0.25177991 | G9: =(Inputs!G10/Inputs!H10)-1 -> 0.22168689 | J9: Flattening | L9: Sales growth = (Current yr sales / past yr sales) - 1
C10: Net earnings | E10: =(Inputs!E21/Inputs!F21)-1 -> 0.3219648 | F10: =(Inputs!F21/Inputs!G21)-1 -> 0.37604907 | G10: =(Inputs!G21/Inputs!H21)-1 -> 0.27731762 | J10: Flattening | L10: Earnings growth = (Current yr earnings / past yr earnings) - 1
C11: EPS-diluted ($) | E11: =(Inputs!E24/Inputs!F24)-1 -> 0.31 | F11: =(Inputs!F24/Inputs!G24)-1 -> 0.35135135 | G11: =(Inputs!G24/Inputs!H24)-1 -> 0.25423729 | J11: Flattening | L11: EPS growth = (Current yr EPS / past yr EPS) - 1
B13: Profitibility Ratios
C14: Gross margins | E14: =(Inputs!E10-Inputs!E11)/Inputs!E10 -> 0.41908708 | F14: =(Inputs!F10-Inputs!F11)/Inputs!F10 -> 0.41431898 | G14: =(Inputs!G10-Inputs!G11)/Inputs!G10 -> 0.41242543 | J14: Increasing | L14: Gross margin = Gross profit / Sales
C15: Operating margins | E15: =Inputs!E14/Inputs!E10 -> 0.14277484 | F15: =Inputs!F14/Inputs!F10 -> 0.13097831 | G15: =Inputs!G14/Inputs!G10 -> 0.11820509 | J15: Sharp increase | L15: Operating margin = Operating profit / Sales
C16: Net margins | E16: =Inputs!E21/Inputs!E10 -> 0.089207614 | F16: =Inputs!F21/Inputs!F10 -> 0.082446243 | G16: =Inputs!G21/Inputs!G10 -> 0.075000632 | J16: Sharp increase | L16: Net margin = Net income / Sales
C18: Return on Assets | E18: =Inputs!E21/AVERAGE(Inputs!E46:F46) -> 0.15808495 | F18: =Inputs!F21/AVERAGE(Inputs!F46:G46) -> 0.15753427 | G18: =Inputs!G21/AVERAGE(Inputs!G46:H46) -> 0.15447085 | J18: Flattening | L18: ROA = Net income / Average total assets of current & past yr
C19: Return on Equity | E19: =Inputs!E21/Inputs!E55 -> 0.20065601 | F19: =Inputs!F21/AVERAGE(Inputs!F55:G55) -> 0.23735023 | G19: =Inputs!G21/AVERAGE(Inputs!G55:H55) -> 0.22978202 | J19: Declining | L19: ROE = Net income / Average shareholders' equity of current and past yr
B21: Liquidity Ratio
C22: Current ratio | E22: =Inputs!E45/Inputs!E50 -> 2.559063 | F22: =Inputs!F45/Inputs!F50 -> 2.3441032 | G22: =Inputs!G45/Inputs!G50 -> 2.399315 | J22: Increasing | L22: Current ratio = Current assets / Current liabilities
C23: Cash ratio | E23: =Inputs!E41/Inputs!E51 -> 0.99129722 | F23: =Inputs!F41/Inputs!F51 -> 0.83672063 | G23: =Inputs!G41/Inputs!G51 -> 0.77643099 | J23: Increasing | L23: Cash ratio = Total cash / Total liabilities
C24: Inventory turnover | E24: =Inputs!E11/Inputs!E43 -> 2.5696233 | F24: =Inputs!F11/Inputs!F43 -> 2.3443103 | G24: =Inputs!G11/Inputs!G43 -> 2.2848074 | J24: Increasing | L24: Inventory turnover = COGS / Inventory

Sheet Scenario Analysis
B2: Bed, Bath & Beyond
B3: Capital Structure Analysis
B6: Scenarios | E6: Actual | F6: Scenario A | G6: Scenario B
B8: Capital Structure Changes
B10: Assumptions
C11: =Inputs!K17 -> Share price ($) | E11: =Inputs!$M$17 -> 37 | F11: n/a | G11: n/a
C12: =Inputs!K18&" used" -> Excess Cash used | E12: =Inputs!$M$18 -> 400000 | F12: n/a | G12: n/a
C13: =Inputs!K10 -> Target debt % | E13: =Inputs!M10 -> 0 | F13: =Inputs!N10 -> 0.4 | G13: =Inputs!O10 -> 0.8
B15: Pro Forma Capital Structure
C16: =Inputs!B27 -> Average shares outstanding-diluted | E16: =Inputs!E27 -> 304690 | F16: =$E$16-F25 -> 276681.14 | G16: =$E$16-G25 -> 259483.08
C17: =Inputs!B55 -> Shareholders' equity | E17: =Inputs!E55 -> 1990820 | F17: =$E$19*(1-F13) -> 954492 | G17: =$E$19*(1-G13) -> 318164
C19: Net Capital | E19: =E17-E12 -> 1590820 | F19: n/a | G19: n/a
C20: New debt issued | E20: =$E$19*E13 -> 0 | F20: =$E$19*F13 -> 636328 | G20: =$E$19*G13 -> 1272656
C21: Interest rate | E21: =Inputs!M12 -> 0 | F21: =Inputs!N12 -> 0.05615 | G21: =Inputs!O12 -> 0.08625
B23: Shares Repurchase
C24: Total buyback value | E24: 0 | F24: =F20+$E$12 -> 1036328 | G24: =G20+$E$12 -> 1672656
C25: Shares repurchased | E25: 0 | F25: =F24/E11 -> 28008.865 | G25: =G24/E11 -> 45206.919
B27: Income Statement Adjustment
B29: =Inputs!B16 -> Interest income | E29: =Inputs!E16 -> 10202 | F29: =$E$29-($E$12*Inputs!$M$23) -> 5492.9952 | G29: =$E$29-($E$12*Inputs!$M$23) -> 5492.9952
B30: =Inputs!B17 -> EBIT | E30: =Inputs!E17 -> 649545 | F30: =$E$30-($E$29-F29) -> 644836 | G30: =$E$30-($E$29-G29) -> 644836
B32: Interest expense | E32: =E20*E21 -> 0 | F32: =F20*F21 -> 35729.817 | G32: =G20*G21 -> 109766.58
B34: Profit before taxes | E34: =E30-E32 -> 649545 | F34: =F30-F32 -> 609106.18 | G34: =G30-G32 -> 535069.42
B36: Taxes | E36: =E34*Inputs!$M$19 -> 250074.83 | F36: =F34*Inputs!$M$19 -> 234505.88 | G36: =G34*Inputs!$M$19 -> 206001.72
B38: Adjusted net income | E38: =E34-E36 -> 399470.17 | F38: =F34-F36 -> 374600.3 | G38: =G34-G36 -> 329067.69
B39: Adjusted EPS-diluted ($) | E39: =E38/E16 -> 1.3110708 | F39: =F38/F16 -> 1.3539062 | G39: =G38/G16 -> 1.2681663
B41: Valuation
B43: Unlevered value | E43: =(E11*E16)-E12 -> 10873530 | F43: =E43 -> 10873530 | G43: =F43 -> 10873530
B44: Present value - tax shield | E44: =Inputs!$M$19*'Scenario Analysis'!E20 -> 0 | F44: =Inputs!$M$19*'Scenario Analysis'!F20 -> 244986.28 | G44: =Inputs!$M$19*'Scenario Analysis'!G20 -> 489972.56
B46: Distress costs | E46: =Inputs!$M$20*'Scenario Analysis'!E43 -> 2174706 | F46: =E46 -> 2174706 | G46: =F46 -> 2174706
B47: Present value - distress costs | E47: =E46*Inputs!M13 -> 0 | F47: =F46*Inputs!N13 -> 39470.914 | G47: =G46*Inputs!O13 -> 980139.99
B49: Levered value | E49: =E43+E44-E47 -> 10873530 | F49: =F43+F44-F47 -> 11079045 | G49: =G43+G44-G47 -> 10383363
B50: ='Historical Analysis'!C19 -> Return on Equity | E50: =E38/E17 -> 0.2006561 | F50: =F38/F17 -> 0.39246039 | G50: =G38/G17 -> 1.0342707
B52: Market Equity value | E52: =E49-E20+E12 -> 11273530 | F52: =F49-F20 -> 10442717 | G52: =G49-G20 -> 9110706.6
B53: Implied share price ($) | E53: =E52/E16 -> 37 | F53: =F52/F16 -> 37.742788 | G53: =G52/G16 -> 35.110985
