Workbook

Sheet Assumptions
A1: Assumptions
A2: Topic | B2: Units
A3: MotionPro Selling Price | B3: 25
A4: TempIQ Selling Price | B4: 30
A5: Q1 Sales % | B5: 0.2
A6: Q2 Sales % | B6: 0.3
A7: Q3 Sales % | B7: 0.2
A8: Q4 Sales % | B8: 0.3
A9: Cash % | B9: 0.6
A10: Credit % | B10: 0.4
A11: Finished Goods Ending % | B11: 0.2
A12: Raw Materials Ending % | B12: 0.1
A13: Chips Cost | B13: 2.75
A14: Casings Cost | B14: 1.5
... A31: TempIQ Req (Casings) | B31: 1

Sheet Opening Balance Sheet
A1: Balance Sheet
A3: Assets | B3: Amount | D3: Liabilities & Equity | E3: Amount
A4: Cash | B4: 50000 | D4: Liabilities | E4: 0
A5: Accounts Receivable | B5: 0 | D5: Equity | E5: 550000
A6: Raw Materials Inventory | B6: =Assumptions!B22 -> 0 | D6: Total Liabilities & Equity | E6: =SUM(E4:E5) -> 550000
A7: Finished Goods Inventory | B7: =Assumptions!B23 -> 0
A8: Fixed Assets | B8: 500000
A9: Total Assets | B9: =SUM(B4:B8) -> 550000

Sheet Sales Budget
A1: Sales Budget
A2: Quarter | B2: MotionPro Units | C2: MotionPro Price | D2: MotionPro Revenue | E2: TempIQ Units | F2: TempIQ Price | G2: TempIQ Revenue | H2: Total Revenue
A3: Q1 | B3: 10000 | C3: =Assumptions!$B$3 -> 25 | D3: =B3*C3 -> 250000 | E3: 8000 | F3: =Assumptions!$B$4 -> 30 | G3: =E3*F3 -> 240000 | H3: =G3+D3 -> 490000
A4: Q2 | B4: 15000 | C4: =Assumptions!$B$3 -> 25 | D4: =B4*C4 -> 375000 | E4: 10000 | F4: =Assumptions!$B$4 -> 30 | G4: =E4*F4 -> 300000 | H4: =G4+D4 -> 675000
A5: Q3 | B5: 12000 | C5: =Assumptions!$B$3 -> 25 | D5: =B5*C5 -> 300000 | E5: 9000 | F5: =Assumptions!$B$4 -> 30 | G5: =E5*F5 -> 270000 | H5: =G5+D5 -> 570000
A6: Q4 | B6: 18000 | C6: =Assumptions!$B$3 -> 25 | D6: =B6*C6 -> 450000 | E6: 12000 | F6: =Assumptions!$B$4 -> 30 | G6: =E6*F6 -> 360000 | H6: =G6+D6 -> 810000
A7: Q1 Y2 | B7: 11000 | C7: =Assumptions!$B$3 -> 25 | D7: =B7*C7 -> 275000 | E7: 9000 | F7: =Assumptions!$B$4 -> 30 | G7: =E7*F7 -> 270000 | H7: =G7+D7 -> 545000

Sheet Production Budget
A1: Production Budget
A2: Quarter | B2: MotionPro BI | C2: MotionPro Production | D2: MotionPro Sales | E2: MotionPro EI | F2: TempIQ BI | G2: TempIQ Production | H2: TempIQ Sales | I2: TempIQ EI
A3: Q1 | B3: 0 | C3: =D3+E3-B3 -> 13000 | D3: ='Sales Budget'!B3 -> 10000 | E3: ='Sales Budget'!B4*Assumptions!B11 -> 3000 | F3: 0 | G3: =H3+I3-F3 -> 10000 | H3: ='Sales Budget'!E3 -> 8000 | I3: ='Sales Budget'!E4*Assumptions!B11 -> 2000
A4: Q2 | B4: =E3 -> 3000 | C4: =D4+E4-B4 -> 14400 | D4: ='Sales Budget'!B4 -> 15000 | E4: ='Sales Budget'!B5*Assumptions!B11 -> 2400 | F4: =I3 -> 2000 | G4: =H4+I4-F4 -> 9800 | H4: ='Sales Budget'!E4 -> 10000 | I4: ='Sales Budget'!E5*Assumptions!B11 -> 1800
A5: Q3 | B5: =E4 -> 2400 | C5: =D5+E5-B5 -> 13200 | D5: ='Sales Budget'!B5 -> 12000 | E5: ='Sales Budget'!B6*Assumptions!B11 -> 3600 | F5: =I4 -> 1800 | G5: =H5+I5-F5 -> 9600 | H5: ='Sales Budget'!E5 -> 9000 | I5: ='Sales Budget'!E6*Assumptions!B11 -> 2400
A6: Q4 | B6: =E5 -> 3600 | C6: =D6+E6-B6 -> 16600 | D6: ='Sales Budget'!B6 -> 18000 | E6: ='Sales Budget'!B7*Assumptions!B11 -> 2200 | F6: =I5 -> 2400 | G6: =H6+I6-F6 -> 11400 | H6: ='Sales Budget'!E6 -> 12000 | I6: ='Sales Budget'!E7*Assumptions!B11 -> 1800

Sheet Raw Materials Budget
A1: Raw Materials Budget
A2: Quarter | B2: MotionPro Chips Needed | C2: MotionPro Casings Needed | D2: TempIQ Chips Needed | E2: TempIQ Casings Needed | F2: Total Chips Needed | G2: Total Casings Needed | H2: Chips Cost | I2: Casings Cost | J2: Total RM Cost
A3: Q1 | B3: ='Production Budget'!C3*Assumptions!$B$28 -> 26000 | C3: =('Production Budget'!C3*Assumptions!$B$29) -> 13000 | D3: =('Production Budget'!G3*Assumptions!$B$30) -> 20000 | E3: =('Production Budget'!G3*Assumptions!$B$31) -> 10000 | F3: =B3+D3 -> 46000 | G3: =C3+E3 -> 23000 | H3: =F3*Assumptions!B13 -> 126500 | I3: =G3*Assumptions!B14 -> 34500 | J3: =H3+I3 -> 161000
A4: Q2 | B4: ='Production Budget'!C4*Assumptions!$B$28 -> 28800 | C4: =('Production Budget'!C4*Assumptions!$B$29) -> 14400 | D4: =('Production Budget'!G4*Assumptions!$B$30) -> 19600 | E4: =('Production Budget'!G4*Assumptions!$B$31) -> 9800 | F4: =B4+D4 -> 48400 | G4: =C4+E4 -> 24200 | H4: =F4*Assumptions!B13 -> 133100 | I4: =G4*Assumptions!B14 -> 36300 | J4: =H4+I4 -> 169400
A5: Q3 | B5: ='Production Budget'!C5*Assumptions!$B$28 -> 26400 | C5: =('Production Budget'!C5*Assumptions!$B$29) -> 13200 | D5: =('Production Budget'!G5*Assumptions!$B$30) -> 19200 | E5: =('Production Budget'!G5*Assumptions!$B$31) -> 9600 | F5: =B5+D5 -> 45600 | G5: =C5+E5 -> 22800 | H5: =F5*Assumptions!B13 -> 125400 | I5: =G5*Assumptions!B14 -> 34200 | J5: =H5+I5 -> 159600
A6: Q4 | B6: ='Production Budget'!C6*Assumptions!$B$28 -> 33200 | C6: =('Production Budget'!C6*Assumptions!$B$29) -> 16600 | D6: =('Production Budget'!G6*Assumptions!$B$30) -> 22800 | E6: =('Production Budget'!G6*Assumptions!$B$31) -> 11400 | F6: =B6+D6 -> 56000 | G6: =C6+E6 -> 28000 | H6: =F6*Assumptions!B13 -> 154000 | I6: =G6*Assumptions!B14 -> 42000 | J6: =H6+I6 -> 196000

Sheet Direct Labor Budget
A1: Direct Labor Budget
A2: Quarter | B2: MotionPro Production | C2: MotionPro Hours/Unit | D2: MotionPro Labor Hours | E2: MotionPro Labor Cost | F2: TempIQ Production | G2: TempIQ Hours/Unit | H2: TempIQ Labor Hours | I2: TempIQ Labor Cost | J2: Total Labor Hours | K2: Total Labor Cost
A3: Q1 | B3: ='Production Budget'!C3 -> 13000 | C3: =Assumptions!B15 -> 0.5 | D3: =B3*C3 -> 6500 | E3: =D3*Assumptions!B17 -> 130000 | F3: ='Production Budget'!G3 -> 10000 | G3: =Assumptions!B16 -> 0.75 | H3: =F3*G3 -> 7500 | I3: =H3*Assumptions!B17 -> 150000 | J3: =D3+H3 -> 14000 | K3: =E3+I3 -> 280000
A4: Q2 | B4: ='Production Budget'!C4 -> 14400 | C4: =Assumptions!B15 -> 0.5 | D4: =B4*C4 -> 7200 | E4: =D4*Assumptions!B17 -> 144000 | F4: ='Production Budget'!G4 -> 9800 | G4: =Assumptions!B16 -> 0.75 | H4: =F4*G4 -> 7350 | I4: =H4*Assumptions!B17 -> 147000 | J4: =D4+H4 -> 14550 | K4: =E4+I4 -> 291000
A5: Q3 | B5: ='Production Budget'!C5 -> 13200 | C5: =Assumptions!B15 -> 0.5 | D5: =B5*C5 -> 6600 | E5: =D5*Assumptions!B17 -> 132000 | F5: ='Production Budget'!G5 -> 9600 | G5: =Assumptions!B16 -> 0.75 | H5: =F5*G5 -> 7200 | I5: =H5*Assumptions!B17 -> 144000 | J5: =D5+H5 -> 13800 | K5: =E5+I5 -> 276000
A6: Q4 | B6: ='Production Budget'!C6 -> 16600 | C6: =Assumptions!B15 -> 0.5 | D6: =B6*C6 -> 8300 | E6: =D6*Assumptions!B17 -> 166000 | F6: ='Production Budget'!G6 -> 11400 | G6: =Assumptions!B16 -> 0.75 | H6: =F6*G6 -> 8550 | I6: =H6*Assumptions!B17 -> 171000 | J6: =D6+H6 -> 16850 | K6: =E6+I6 -> 337000

Sheet Factory Overhead Budget
A1: Factory Overhead Budget
A2: Quarter | B2: Total Direct Labor Hours | C2: Variable OH Rate | D2: Variable OH Cost | E2: Fixed OH | F2: Depreciation | G2: Total Factory OH
A3: Q1 | B3: ='Direct Labor Budget'!J3 -> 14000 | C3: 5 | D3: =B3*C3 -> 70000 | E3: 75000 | F3: =Assumptions!B25*10%/4 -> 12500 | G3: =D3+E3+F3 -> 157500
A4: Q2 | B4: ='Direct Labor Budget'!J4 -> 14550 | C4: 5 | D4: =B4*C4 -> 72750 | E4: 75000 | F4: =Assumptions!B25*10%/4 -> 12500 | G4: =D4+E4+F4 -> 160250
A5: Q3 | B5: ='Direct Labor Budget'!J5 -> 13800 | C5: 5 | D5: =B5*C5 -> 69000 | E5: 75000 | F5: =Assumptions!B25*10%/4 -> 12500 | G5: =D5+E5+F5 -> 156500
A6: Q4 | B6: ='Direct Labor Budget'!J6 -> 16850 | C6: 5 | D6: =B6*C6 -> 84250 | E6: 75000 | F6: =Assumptions!B25*10%/4 -> 12500 | G6: =D6+E6+F6 -> 171750

Sheet Finished Goods Inventory Budget
A1: Finished Goods Inventory Budget
A2: Quarter | B2: MotionPro Unit Cost | C2: MotionPro Ending Units | D2: MotionPro EI Value | E2: TempIQ Unit Cost | F2: TempIQ Ending Units | G2: TempIQ EI Value
A3: Q1 | B3: =(Assumptions!$B$28*Assumptions!$B$13)+(Assumptions!$B$29*Assumptions!$B$14)+(Assumptions!$B$15*Assumptions!$B$17)+(Assumptions!$B$15*5)+('Factory Overhead Budget'!$E$3/('Production Budget'!C3+'Production Budget'!G3)) -> 22.76087 | C3: ='Production Budget'!E3 -> 3000 | D3: =B3*C3 -> 68282.609 | E3: =(Assumptions!$B$28*Assumptions!$B$13)+(Assumptions!$B$31*Assumptions!$B$14)+(Assumptions!$B$16*Assumptions!$B$17)+(Assumptions!$B$16*5)+('Factory Overhead Budget'!$E$3/('Production Budget'!C3+'Production Budget'!G3)) -> 29.01087 | F3: ='Production Budget'!I3 -> 2000 | G3: =E3*F3 -> 58021.739
A4: Q2 | B4: =(Assumptions!$B$28*Assumptions!$B$13)+(Assumptions!$B$29*Assumptions!$B$14)+(Assumptions!$B$15*Assumptions!$B$17)+(Assumptions!$B$15*5)+('Factory Overhead Budget'!$E$3/('Production Budget'!C4+'Production Budget'!G4)) -> 22.599174 | C4: ='Production Budget'!E4 -> 2400 | D4: =B4*C4 -> 54238.017 | E4: =(Assumptions!$B$28*Assumptions!$B$13)+(Assumptions!$B$31*Assumptions!$B$14)+(Assumptions!$B$16*Assumptions!$B$17)+(Assumptions!$B$16*5)+('Factory Overhead Budget'!$E$3/('Production Budget'!C4+'Production Budget'!G4)) -> 28.849174 | F4: ='Production Budget'!I4 -> 1800 | G4: =E4*F4 -> 51928.512
A5: Q3 | B5: =(Assumptions!$B$28*Assumptions!$B$13)+(Assumptions!$B$29*Assumptions!$B$14)+(Assumptions!$B$15*Assumptions!$B$17)+(Assumptions!$B$15*5)+('Factory Overhead Budget'!$E$3/('Production Budget'!C5+'Production Budget'!G5)) -> 22.789474 | C5: ='Production Budget'!E5 -> 3600 | D5: =B5*C5 -> 82042.105 | E5: =(Assumptions!$B$28*Assumptions!$B$13)+(Assumptions!$B$31*Assumptions!$B$14)+(Assumptions!$B$16*Assumptions!$B$17)+(Assumptions!$B$16*5)+('Factory Overhead Budget'!$E$3/('Production Budget'!C5+'Production Budget'!G5)) -> 29.039474 | F5: ='Production Budget'!I5 -> 2400 | G5: =E5*F5 -> 69694.737
A6: Q4 | B6: =(Assumptions!$B$28*Assumptions!$B$13)+(Assumptions!$B$29*Assumptions!$B$14)+(Assumptions!$B$15*Assumptions!$B$17)+(Assumptions!$B$15*5)+('Factory Overhead Budget'!$E$3/('Production Budget'!C6+'Production Budget'!G6)) -> 22.178571 | C6: ='Production Budget'!E6 -> 2200 | D6: =B6*C6 -> 48792.857 | E6: =(Assumptions!$B$28*Assumptions!$B$13)+(Assumptions!$B$31*Assumptions!$B$14)+(Assumptions!$B$16*Assumptions!$B$17)+(Assumptions!$B$16*5)+('Factory Overhead Budget'!$E$3/('Production Budget'!C6+'Production Budget'!G6)) -> 28.428571 | F6: ='Production Budget'!I6 -> 1800 | G6: =E6*F6 -> 51171.429

Sheet SG&A Budget
A1: SG&A Budget
A2: Quarter | B2: Units Sold | C2: Variable Cost per Unit | D2: Variable SG&A | E2: Fixed SG&A | F2: Total SG&A
A3: Q1 | B3: ='Sales Budget'!B3+'Sales Budget'!E3 -> 18000 | C3: 2 | D3: =B3*C3 -> 36000 | E3: 50000 | F3: =D3+E3 -> 86000
A4: Q2 | B4: ='Sales Budget'!B4+'Sales Budget'!E4 -> 25000 | C4: 2 | D4: =B4*C4 -> 50000 | E4: 50000 | F4: =D4+E4 -> 100000
A5: Q3 | B5: ='Sales Budget'!B5+'Sales Budget'!E5 -> 21000 | C5: 2 | D5: =B5*C5 -> 42000 | E5: 50000 | F5: =D5+E5 -> 92000
A6: Q4 | B6: ='Sales Budget'!B6+'Sales Budget'!E6 -> 30000 | C6: 2 | D6: =B6*C6 -> 60000 | E6: 50000 | F6: =D6+E6 -> 110000

Sheet Cash Budget
A1: Cash Budget
A2: Quarter | B2: Beginning Cash | C2: Cash Inflows | D2: RM Payments | E2: Labor Payments | F2: FOH Payments | G2: SG&A Payments | H2: Total Cash Outflows | I2: Cash Surplus/Deficit | J2: Borrowing | K2: Ending Cash
A3: Q1 | B3: =Assumptions!B21 -> 50000 | C3: =(0.6*'Sales Budget'!H3) -> 294000 | D3: =0.4*'Raw Materials Budget'!J3 -> 64400 | E3: ='Direct Labor Budget'!K3 -> 280000 | F3: ='Factory Overhead Budget'!G3-'Factory Overhead Budget'!F3 -> 145000 | G3: ='SG&A Budget'!F3 -> 86000 | H3: =SUM(D3:G3) -> 575400 | I3: =B3+C3-H3 -> -231400 | J3: =MAX(0,50000-I3) -> 281400 | K3: =I3+J3 -> 50000
A4: Q2 | B4: =K3 -> 50000 | C4: =(0.6*'Sales Budget'!H4)+(0.4*'Sales Budget'!H3) -> 601000 | D4: ='Raw Materials Budget'!J4*0.4 + 'Raw Materials Budget'!J3*0.4 -> 132160 | E4: ='Direct Labor Budget'!K4 -> 291000 | F4: ='Factory Overhead Budget'!G4-'Factory Overhead Budget'!F4 -> 147750 | G4: ='SG&A Budget'!F4 -> 100000 | H4: =SUM(D4:G4) -> 670910 | I4: =B4+C4-H4 -> -19910 | J4: =MAX(0,50000-I4) -> 69910 | K4: =I4+J4 -> 50000
A5: Q3 | B5: =K4 -> 50000 | C5: =(0.6*'Sales Budget'!H5)+(0.4*'Sales Budget'!H4) -> 612000 | D5: ='Raw Materials Budget'!J5*0.4 + 'Raw Materials Budget'!J4*0.4 + 'Raw Materials Budget'!J3*0.2 -> 163800 | E5: ='Direct Labor Budget'!K5 -> 276000 | F5: ='Factory Overhead Budget'!G5-'Factory Overhead Budget'!F5 -> 144000 | G5: ='SG&A Budget'!F5 -> 92000 | H5: =SUM(D5:G5) -> 675800 | I5: =B5+C5-H5 -> -13800 | J5: =MAX(0,50000-I5) -> 63800 | K5: =I5+J5 -> 50000
A6: Q4 | B6: =K5 -> 50000 | C6: =(0.6*'Sales Budget'!H6)+(0.4*'Sales Budget'!H5) -> 714000 | D6: ='Raw Materials Budget'!J6*0.4 + 'Raw Materials Budget'!J5*0.4 + 'Raw Materials Budget'!J4*0.2 -> 176120 | E6: ='Direct Labor Budget'!K6 -> 337000 | F6: ='Factory Overhead Budget'!G6-'Factory Overhead Budget'!F6 -> 159250 | G6: ='SG&A Budget'!F6 -> 110000 | H6: =SUM(D6:G6) -> 782370 | I6: =B6+C6-H6 -> -18370 | J6: =MAX(0,50000-I6) -> 68370 | K6: =I6+J6 -> 50000

Sheet Income Statement
A1: Income Statement
A2: Quarter | B2: Revenue | C2: COGS | D2: Gross Profit | E2: SG&A | F2: Operating Income | G2: Interest Expense | H2: Pretax Income | I2: Taxes (25%) | J2: Net Income
A3: Q1 | B3: ='Sales Budget'!H3 -> 490000 | C3: =('Finished Goods Inventory Budget'!$B$3*'Sales Budget'!B3)+('Finished Goods Inventory Budget'!$E$3*'Sales Budget'!E3) -> 459695.65 | D3: =B3-C3 -> 30304.348 | E3: ='SG&A Budget'!F3 -> 86000 | F3: =D3-E3 -> -55695.652 | G3: ='Cash Budget'!J3*0.06/4 -> 4221 | H3: =F3-G3 -> -59916.652 | I3: =MAX(0,H3*0.25) -> 0 | J3: =H3-I3 -> -59916.652
A4: Q2 | B4: ='Sales Budget'!H4 -> 675000 | C4: =('Finished Goods Inventory Budget'!$B$3*'Sales Budget'!B4)+('Finished Goods Inventory Budget'!$E$3*'Sales Budget'!E4) -> 631521.74 | D4: =B4-C4 -> 43478.261 | E4: ='SG&A Budget'!F4 -> 100000 | F4: =D4-E4 -> -56521.739 | G4: ='Cash Budget'!J4*0.06/4 -> 1048.65 | H4: =F4-G4 -> -57570.389 | I4: =MAX(0,H4*0.25) -> 0 | J4: =H4-I4 -> -57570.389
A5: Q3 | B5: ='Sales Budget'!H5 -> 570000 | C5: =('Finished Goods Inventory Budget'!$B$3*'Sales Budget'!B5)+('Finished Goods Inventory Budget'!$E$3*'Sales Budget'!E5) -> 534228.26 | D5: =B5-C5 -> 35771.739 | E5: ='SG&A Budget'!F5 -> 92000 | F5: =D5-E5 -> -56228.261 | G5: ='Cash Budget'!J5*0.06/4 -> 957 | H5: =F5-G5 -> -57185.261 | I5: =MAX(0,H5*0.25) -> 0 | J5: =H5-I5 -> -57185.261
A6: Q4 | B6: ='Sales Budget'!H6 -> 810000 | C6: =('Finished Goods Inventory Budget'!$B$3*'Sales Budget'!B6)+('Finished Goods Inventory Budget'!$E$3*'Sales Budget'!E6) -> 757826.09 | D6: =B6-C6 -> 52173.913 | E6: ='SG&A Budget'!F6 -> 110000 | F6: =D6-E6 -> -57826.087 | G6: ='Cash Budget'!J6*0.06/4 -> 1025.55 | H6: =F6-G6 -> -58851.637 | I6: =MAX(0,H6*0.25) -> 0 | J6: =H6-I6 -> -58851.637
A8: Y1 Total | J8: =SUM(J3:J6) -> -233523.94

Sheet Statement of Retained Earnings
A1: Statement of Retained Earnings
A2: Quarter | B2: Beginning Retained Earnings | C2: Net Income | D2: Dividends Paid | E2: Ending Retained Earnings
A3: Q1 | B3: 0 | C3: ='Income Statement'!J3 -> -59916.652 | D3: 31250 | E3: =B3+C3-D3 -> -91166.652
A4: Q2 | B4: =E3 -> -91166.652 | C4: ='Income Statement'!J4 -> -57570.389 | D4: 31250 | E4: =B4+C4-D4 -> -179987.04
A5: Q3 | B5: =E4 -> -179987.04 | C5: ='Income Statement'!J5 -> -57185.261 | D5: 31250 | E5: =B5+C5-D5 -> -268422.3
A6: Q4 | B6: =E5 -> -268422.3 | C6: ='Income Statement'!J6 -> -58851.637 | D6: 31250 | E6: =B6+C6-D6 -> -358523.94

Sheet Closing Balance Sheet
A1: Closing Balance Sheet
A2: Item | B2: Amount
A3: Cash | B3: 50000
A4: Accounts Receivable | B4: =('Sales Budget'!D6+'Sales Budget'!H6)*0.4 -> 504000
A5: Raw Materials Inventory | B5: ='Raw Materials Budget'!J6 -> 196000
A6: Finished Goods Inventory | B6: ='Finished Goods Inventory Budget'!D6+'Finished Goods Inventory Budget'!G6 -> 99964.286
A7: Fixed Assets (net of depreciation) | B7: =Assumptions!B25-'Factory Overhead Budget'!F3-'Factory Overhead Budget'!F4-'Factory Overhead Budget'!F5-'Factory Overhead Budget'!F6 -> 450000
A8: Total Assets | B8: =SUM(B3:B7) -> 1299964.3
A9: Accounts Payable | B9: ='Raw Materials Budget'!J6*0.6 -> 117600
A10: Accrued Interest | B10: =SUM('Cash Budget'!G3:G6) -> 388000
A11: Total Liabilities | B11: =SUM(B9:B10) -> 505600
A12: Equity (Retained Earnings + Capital) | B12: =B8-B11 -> 794364.29
A13: Total Liabilities & Equity | B13: =B11+B12 -> 1299964.3

Sheet Statement of Cash Flows
A1: Statement of Cash Flows
A2: Quarter | B2: Net Income | C2: Depreciation | D2: Change in AR | E2: Change in Inventory | F2: Change in AP | G2: Cash from Operations
A3: Q1 | B3: ='Income Statement'!J3 -> -59916.652 | C3: ='Factory Overhead Budget'!F3 -> 12500 | D3: =0 -> 0 | E3: =0 -> 0 | F3: ='Raw Materials Budget'!J3*0.6 -> 96600 | G3: =B3+C3-D3-E3+F3 -> 49183.348
A4: Q2 | B4: ='Income Statement'!J4 -> -57570.389 | C4: ='Factory Overhead Budget'!F4 -> 12500 | D4: ='Sales Budget'!D3*0.4+'Sales Budget'!H3*0.4 -> 296000 | E4: =('Raw Materials Budget'!J4-'Raw Materials Budget'!J3) + ('Finished Goods Inventory Budget'!D4+'Finished Goods Inventory Budget'!G4-('Finished Goods Inventory Budget'!D3+'Finished Goods Inventory Budget'!G3)) -> -11737.819 | F4: ='Raw Materials Budget'!J4*0.6 -> 101640 | G4: =B4+C4-D4-E4+F4 -> -227692.57
A5: Q3 | B5: ='Income Statement'!J5 -> -57185.261 | C5: ='Factory Overhead Budget'!F5 -> 12500 | D5: ='Sales Budget'!D4*0.4+'Sales Budget'!H4*0.4 -> 420000 | E5: =('Raw Materials Budget'!J5-'Raw Materials Budget'!J4) + ('Finished Goods Inventory Budget'!D5+'Finished Goods Inventory Budget'!G5-('Finished Goods Inventory Budget'!D4+'Finished Goods Inventory Budget'!G4)) -> 35770.313 | F5: ='Raw Materials Budget'!J5*0.6 -> 95760 | G5: =B5+C5-D5-E5+F5 -> -404695.57
A6: Q4 | B6: ='Income Statement'!J6 -> -58851.637 | C6: ='Factory Overhead Budget'!F6 -> 12500 | D6: ='Sales Budget'!D5*0.4+'Sales Budget'!H5*0.4 -> 348000 | E6: =('Raw Materials Budget'!J6-'Raw Materials Budget'!J5) + ('Finished Goods Inventory Budget'!D6+'Finished Goods Inventory Budget'!G6-('Finished Goods Inventory Budget'!D5+'Finished Goods Inventory Budget'!G5)) -> -15372.556 | F6: ='Raw Materials Budget'!J6*0.6 -> 117600 | G6: =B6+C6-D6-E6+F6 -> -261379.08
